Workbook

Sheet Metta_Invest
B10: CONFIGURAÇÕES
B11: Salário | D11: 5000
B12: Redimento Carteira | D12: 0.006
B13: Sugestão de Investimento (30%) | D13: =D11*30% -> 1500
B15: INVESTIMENTO MENSAL
B16: Quanto Investir por mês? | D16: 500
B17: Por Quantos Anos? | D17: 10
B18: Taxa de Rendimento mensal? | D18: 0.01079
B19: Patrimônio acumulado? | D19: =FV(D18,D17*12,D16*-1) -> 121642.11
B20: Dividendos Mensais? | D20: =D19*$D$12 -> 729.85264
B22: CENÁRIOS | D22: Dividendo
A23: 2 | B23: Quanto em 2 Anos | C23: =FV($D$18,$A23*12,$D$16*-1) -> 13613.814 | D23: =C23*$D$12 -> 81.682882
A24: 5 | B24: Quanto em 5 Anos | C24: =FV($D$18,$A24*12,$D$16*-1) -> 41888.457 | D24: =C24*$D$12 -> 251.33074
A25: 10 | B25: Quanto em 10 Anos | C25: =FV($D$18,$A25*12,$D$16*-1) -> 121642.11 | D25: =C25*$D$12 -> 729.85264
A26: 20 | B26: Quanto em 20 Anos | C26: =FV($D$18,$A26*12,$D$16*-1) -> 562599.2 | D26: =C26*$D$12 -> 3375.5952
A27: 30 | B27: Quanto em 30 Anos | C27: =FV($D$18,$A27*12,$D$16*-1) -> 2161084.8 | D27: =C27*$D$12 -> 12966.509
B31: PERFIL | C31: Moderado
B32: VALOR A SER INVESTIDO POR MÊS | C32: =D16 -> 500
B34: TIPO DE FII | C34: Percentual Sugerido | D34: Valores
B35: TIJOLO | C35: =VLOOKUP($C$31&"-"&B35,Planilha1!$A:$D,4,FALSE) -> 0.4 | D35: =C35*$C$32 -> 200
B36: PAPEL | C36: =VLOOKUP($C$31&"-"&B36,Planilha1!$A:$D,4,FALSE) -> 0.32 | D36: =C36*$C$32 -> 160
B37: HÍBRIDOS | C37: =VLOOKUP($C$31&"-"&B37,Planilha1!$A:$D,4,FALSE) -> 0.08 | D37: =C37*$C$32 -> 40
B38: FOFs | C38: =VLOOKUP($C$31&"-"&B38,Planilha1!$A:$D,4,FALSE) -> 0.1 | D38: =C38*$C$32 -> 50
B39: DESENVOLVIMENTO | C39: =VLOOKUP($C$31&"-"&B39,Planilha1!$A:$D,4,FALSE) -> 0.05 | D39: =C39*$C$32 -> 25
B40: HOTELARIAS | C40: =VLOOKUP($C$31&"-"&B40,Planilha1!$A:$D,4,FALSE) -> 0.05 | D40: =C40*$C$32 -> 25
D41: =SUM(D35:D40) -> 500

Sheet Planilha1
A2: CHAVE | B2: PERFIL | C2: TIPO DE FII | D2: Percentual Sugerido
A3: =B3&"-"&C3 -> Conservador-TIJOLO | B3: Conservador | C3: TIJOLO | D3: 0.5 | I3: %
A4: =B4&"-"&C4 -> Conservador-PAPEL | B4: Conservador | C4: PAPEL | D4: 0.3 | H4: Moderado-TIJOLO | I4: =VLOOKUP(H4,$A:$D,4,FALSE) -> 0.4
A5: =B5&"-"&C5 -> Conservador-HÍBRIDOS | B5: Conservador | C5: HÍBRIDOS | D5: 0.1
A6: =B6&"-"&C6 -> Conservador-FOFs | B6: Conservador | C6: FOFs | D6: 0.1
A7: =B7&"-"&C7 -> Conservador-DESENVOLVIMENTO | B7: Conservador | C7: DESENVOLVIMENTO | D7: 0
A8: =B8&"-"&C8 -> Conservador-HOTELARIAS | B8: Conservador | C8: HOTELARIAS | D8: 0
A9: =B9&"-"&C9 -> Moderado-TIJOLO | B9: Moderado | C9: TIJOLO | D9: 0.4
A10: =B10&"-"&C10 -> Moderado-PAPEL | B10: Moderado | C10: PAPEL | D10: 0.32
A11: =B11&"-"&C11 -> Moderado-HÍBRIDOS | B11: Moderado | C11: HÍBRIDOS | D11: 0.08
A12: =B12&"-"&C12 -> Moderado-FOFs | B12: Moderado | C12: FOFs | D12: 0.1
A13: =B13&"-"&C13 -> Moderado-DESENVOLVIMENTO | B13: Moderado | C13: DESENVOLVIMENTO | D13: 0.05
A14: =B14&"-"&C14 -> Moderado-HOTELARIAS | B14: Moderado | C14: HOTELARIAS | D14: 0.05
A15: =B15&"-"&C15 -> Agressivo-TIJOLO | B15: Agressivo | C15: TIJOLO | D15: 0.1
A16: =B16&"-"&C16 -> Agressivo-PAPEL | B16: Agressivo | C16: PAPEL | D16: 0.5
... A20: =B20&"-"&C20 -> Agressivo-HOTELARIAS | B20: Agressivo | C20: HOTELARIAS | D20: 0.1
